baicai_dev/__init__.py
baicai_dev/agents/__init__.py
baicai_dev/agents/graphs/__init__.py
baicai_dev/agents/graphs/action_builder/__init__.py
baicai_dev/agents/graphs/action_builder/action_builder.py
baicai_dev/agents/graphs/action_builder/nodes/__init__.py
baicai_dev/agents/graphs/action_builder/nodes/action_coder_node.py
baicai_dev/agents/graphs/action_builder/nodes/action_debugger_node.py
baicai_dev/agents/graphs/action_builder/nodes/action_evaluator_node.py
baicai_dev/agents/graphs/action_builder/nodes/reasoner_node.py
baicai_dev/agents/graphs/action_builder/nodes/run_action_coder_node.py
baicai_dev/agents/graphs/action_builder/state.py
baicai_dev/agents/graphs/baseline_builder/__init__.py
baicai_dev/agents/graphs/baseline_builder/baseline_builder.py
baicai_dev/agents/graphs/baseline_builder/nodes/__init__.py
baicai_dev/agents/graphs/baseline_builder/nodes/baseline_coder_node.py
baicai_dev/agents/graphs/baseline_builder/state.py
baicai_dev/agents/graphs/dl_builder/__init__.py
baicai_dev/agents/graphs/dl_builder/dl_builder.py
baicai_dev/agents/graphs/dl_builder/nodes/__init__.py
baicai_dev/agents/graphs/dl_builder/nodes/dl_coder_node.py
baicai_dev/agents/graphs/dl_builder/nodes/dl_debugger_node.py
baicai_dev/agents/graphs/dl_builder/state.py
baicai_dev/agents/graphs/ml_graph.py
baicai_dev/agents/graphs/optimization_builder/__init__.py
baicai_dev/agents/graphs/optimization_builder/nodes/__init__.py
baicai_dev/agents/graphs/optimization_builder/nodes/hyperparam_tuner_node.py
baicai_dev/agents/graphs/optimization_builder/optimization_builder.py
baicai_dev/agents/graphs/optimization_builder/state.py
baicai_dev/agents/graphs/workflow_builder/__init__.py
baicai_dev/agents/graphs/workflow_builder/nodes/__init__.py
baicai_dev/agents/graphs/workflow_builder/nodes/workflow_coder_node.py
baicai_dev/agents/graphs/workflow_builder/state.py
baicai_dev/agents/graphs/workflow_builder/workflow_builder.py
baicai_dev/agents/roles/__init__.py
baicai_dev/agents/roles/dl/__init__.py
baicai_dev-0.1.0.dist-info/METADATA
baicai_dev-0.1.0.dist-info/WHEEL
baicai_dev-0.1.0.dist-info/entry_points.txt
baicai_dev-0.1.0.dist-info/RECORD
