Metadata-Version: 2.3
Name: baicai-dev
Version: 0.1.0
Summary: Development package for Baicai
License: MIT
Keywords: python,agent,AI,machine learning,LLM
Author: Zhaoyang tech
Author-email: gengyabc@aliyun.com
Requires-Python: >=3.10,<3.12
Classifier: License :: OSI Approved :: MIT License
Classifier: Programming Language :: Python :: 3
Classifier: Programming Language :: Python :: 3.10
Classifier: Programming Language :: Python :: 3.11
Requires-Dist: accelerate (==0.28.0)
Requires-Dist: baicai-base (==0.1.2)
Requires-Dist: catboost (>=1.2.7)
Requires-Dist: datasets (>=3.2.0)
Requires-Dist: fastai (>=2.7.18)
Requires-Dist: lightgbm (>=4.6.0,<5.0.0)
Requires-Dist: pandas (>=2.2.3,<3.0.0)
Requires-Dist: plotly (>=6.0.0,<7.0.0)
Requires-Dist: scikit-learn (>=1.6.1)
Requires-Dist: seaborn (>=0.13.2,<0.14.0)
Requires-Dist: sentence-transformers (==2.5.1)
Requires-Dist: shap (>=0.47.0,<0.48.0)
Requires-Dist: statsmodels (>=0.14.4,<0.15.0)
Requires-Dist: torch (>=2.5.1)
Requires-Dist: torchaudio (>=2.5.1)
Requires-Dist: torchvision (>=0.20.1)
Requires-Dist: transformers (>=4.38.2)
Requires-Dist: xgboost (>=3.0.0,<4.0.0)
